odoo8_addon_hr_webcam-8.0.1.0.0.99.dev11-py2.7-nspkg.pth
odoo8_addon_hr_webcam-8.0.1.0.0.99.dev11.dist-info/DESCRIPTION.rst
odoo8_addon_hr_webcam-8.0.1.0.0.99.dev11.dist-info/METADATA
odoo8_addon_hr_webcam-8.0.1.0.0.99.dev11.dist-info/RECORD
odoo8_addon_hr_webcam-8.0.1.0.0.99.dev11.dist-info/WHEEL
odoo8_addon_hr_webcam-8.0.1.0.0.99.dev11.dist-info/metadata.json
odoo8_addon_hr_webcam-8.0.1.0.0.99.dev11.dist-info/namespace_packages.txt
odoo8_addon_hr_webcam-8.0.1.0.0.99.dev11.dist-info/top_level.txt
odoo_addons/hr_webcam/README.rst
odoo_addons/hr_webcam/__init__.py
odoo_addons/hr_webcam/__openerp__.py
odoo_addons/hr_webcam/hr_employee.py
odoo_addons/hr_webcam/hr_webcam.xml
odoo_addons/hr_webcam/hr_webcam_data.xml
odoo_addons/hr_webcam/hr_webcam_view.xml
odoo_addons/hr_webcam/i18n/ar.po
odoo_addons/hr_webcam/i18n/de.po
odoo_addons/hr_webcam/i18n/es.po
odoo_addons/hr_webcam/i18n/fi.po
odoo_addons/hr_webcam/i18n/fr.po
odoo_addons/hr_webcam/i18n/hr_webcam.pot
odoo_addons/hr_webcam/i18n/it.po
odoo_addons/hr_webcam/i18n/nl.po
odoo_addons/hr_webcam/i18n/nl_NL.po
odoo_addons/hr_webcam/i18n/pt_BR.po
odoo_addons/hr_webcam/i18n/ro.po
odoo_addons/hr_webcam/i18n/sl.po
odoo_addons/hr_webcam/static/jscam.swf
odoo_addons/hr_webcam/static/jscam_canvas_only.swf
odoo_addons/hr_webcam/static/description/icon.png
odoo_addons/hr_webcam/static/src/css/hr_webcam.css
odoo_addons/hr_webcam/static/src/js/hr_webcam.js
odoo_addons/hr_webcam/static/src/js/jquery.webcam.js
odoo_addons/hr_webcam/static/src/xml/hr_webcam.xml
